<?xml version="1.0" encoding="utf-8"?>
<odoo>
<data>
	<record id="view_account_financial_report__inherit_form" model="ir.ui.view">
    <field name="name">account.financial.html.report.inherit.form</field>
    <field name="model">account.financial.html.report</field>
    <field name="inherit_id" ref="account_reports.view_account_financial_report_form" />
		<field name="arch" type="xml">
			<field name="show_journal_filter" position="after">
				<field name="show_operating_filter"/>
			</field>
		</field>
	</record>
</data>
</odoo>